picutils/__init__.py
picutils/base.py
picutils/del_entire_folder.py
picutils/html_index.py
picutils/html_viewer.py
picutils/move_out.py
picutils/processPics.py
picutils/process_pics.py
picutils-0.1.6.8.9.dist-info/DESCRIPTION.rst
picutils-0.1.6.8.9.dist-info/METADATA
picutils-0.1.6.8.9.dist-info/RECORD
picutils-0.1.6.8.9.dist-info/WHEEL
picutils-0.1.6.8.9.dist-info/entry_points.txt
picutils-0.1.6.8.9.dist-info/metadata.json
picutils-0.1.6.8.9.dist-info/top_level.txt
