Metadata-Version: 2.0
Name: picutils
Version: 0.1.6.8.9
Summary: Hosting pictures into html, website, python Flask and GUI, image manupilation
Home-page: https://github.com/shichaoji/picutils
Author: Shichao(Richard) Ji
Author-email: jshichao@vt.edu
License: MIT
Download-URL: https://github.com/shichaoji/picutils/archive/0.1.tar.gz
Keywords: hosting,picture,image,python,flask
Platform: UNKNOWN
Classifier: License :: OSI Approved :: MIT License
Classifier: Programming Language :: Python :: 2
Classifier: Programming Language :: Python :: 3
Requires-Dist: Pillow
Requires-Dist: natsort
